mdr_python_api/__init__.py
mdr_python_api/api.py
mdr_python_api/code-flow.json
mdr_python_api/example.py
mdr_python_api/http_api.py
mdr_python_api/input.py
mdr_python_api/loop_back_server.py
mdr_python_api/oidc_common.py
mdr_python_api/tcp_api.py
mdr_python_api/token_generator.py
mdr_python_api/token_manager.py
mdr_python_api-1.1.5.dist-info/METADATA
mdr_python_api-1.1.5.dist-info/WHEEL
mdr_python_api-1.1.5.dist-info/top_level.txt
mdr_python_api-1.1.5.dist-info/RECORD
