Metadata-Version: 2.1
Name: mdr_python_api
Version: 1.1.5
Requires-Dist: requests
Requires-Dist: jwcrypto
